{
  "ids": {
    "users": {
      "main": "628241756235890708",
      "jphelp": "786909743649390602",
      "407": "976840669870051368",
      "dream": "931027453281984522",
      "omega": "855711160393662464",

      "dyno": "155149108183695360",
      "sigma": "216437513709944832",
      "mee6": "159985870458322944",
      "rroles": "550613223733329920",
      "kotoba": "251239170058616833",
      "sora": "750260711460175894"
    },
    "guilds": {
      "jp101": "778426035141869620",
      "407": "976680311175905361",
      "holorpg": "779150625433976864",
      "pain": "847136199436009502"
    },
    "channels": {
      "jp101": {
        "announcements": "779953766341410847",
        "rules": "778430643901825044",
        "boost-status": "969852761174851646",
        "mod-logs": "805444415443173376",
        "file-logs": "808218683288584232",
        "role-logs": "805443587574988810",
        "mod-test": "779380025299959829",
        "hangout": "778426035737329684",
        "nihongo-centre": "778965985360609290",
        "q-a": "778855628725813258",
        "wotd-n4": "787856481209810994",
        "wotd-n3": "787857267310985236",
        "wotd-n2": "787857545975955466",
        "voice-channels": "778426035737329685"
      },
      "407": {
        "bot-spam": "979051736176160828"
      },
      "holorpg": {
        "bot-test": "779656843919753227"
      },
      "pain": {
        "general": "847292548589289513"
      }
    },
    "roles": {
      "jp101": {
        "mod": "778434956891783170",
        "contributor": "813758503113457675",
        "bots": "778961297987207208"
      },
      "407": {
        "sci-math": "976685826870247504",
        "bot": "976700948653178900"
      },
      "pain": {
        "god": "855710404117397524",
        "member": "855150270467538954",
        "bot": "855146634118430720"
      }
    },
    "emojis": {
      "jp101": {
        "inui_lurk": "832578938428456990",
        "inui_pat": "934994354857205760",
        "mio_stare": "855699348428029963",
        "mio_pat": "855699348657799179",
        "mio_hey": "855699348763050034",
        "a_mio_hey": "855699349445935125"
      }
    }
  },
  "main": {
    "jphelp": {
      "guild": "jp101",
      "channel": "mod-test"
    },
    "407": {
      "guild": "407",
      "channel": "bot-spam"
    },
    "dream": {
      "guild": "holorpg",
      "channel": "bot-test"
    },
    "omega": {
      "guild": "pain",
      "channel": "general"
    }
  },
  "color": {
    "nitro": "ff73fa",

    "dyno": "2473c7",
    "sigma": "0c392f",
    "mee6": "64cdf9",
    "rroles": "c82789",
    "kotoba": "a2817d",
    "sora": "e6d5d4"
  },
  "config": {
    "nc_manage-exempt": [
      "q-a",
      "wotd-n4",
      "wotd-n3",
      "wotd-n2"
    ],
    "botPresence": {
      "jphelp": [
        "dyno",
        "sigma",
        "mee6",
        "rroles",
        "kotoba",
        "sora"
      ],
      "omega": [
        "jphelp",
        "dream",
        "407"
      ]
    },
    "autoRole": {
      "jphelp": [null, "bots", "role-logs"],
      "407": ["sci-math", "bot", null],
      "omega": ["member", "bot", null]
    },
    "vanity": {
      "jphelp": "jp101"
    },
    "genLogs": {
      "jphelp": ["mod-logs"]
    }
  }
}
